CaseOpenerAPI/__init__.py
CaseOpenerAPI/skins.py
CaseOpenerAPI-0.1.2.dist-info/METADATA
CaseOpenerAPI-0.1.2.dist-info/WHEEL
CaseOpenerAPI-0.1.2.dist-info/top_level.txt
CaseOpenerAPI-0.1.2.dist-info/RECORD
