Metadata-Version: 2.2
Name: CaseOpenerAPI
Version: 0.1.2
Summary: Case Opener api tools
Author: Markshubat
Author-email: markshubat@gmail.com
Keywords: skin generation caseopener
Classifier: Programming Language :: Python :: 3.12
Classifier: Operating System :: OS Independent
Requires-Python: >=3.6
Requires-Dist: requests>=2.25.1
Requires-Dist: tqdm
Dynamic: author
Dynamic: author-email
Dynamic: classifier
Dynamic: description
Dynamic: description-content-type
Dynamic: keywords
Dynamic: requires-dist
Dynamic: requires-python
Dynamic: summary
